sudoku_ocr/__init__.py
sudoku_ocr/board.py
sudoku_ocr/cnn.h5
sudoku_ocr/image.py
sudoku_ocr/version.py
tests/__init__.py
tests/test_board.py
tests/test_image.py
tests/img/no_sudoku.jpg
tests/img/no_sudoku2.jpg
tests/img/sudoku1.png
tests/img/sudoku2.jpg
tests/img/sudoku3.jpg
sudoku_ocr-1.1.3.dist-info/LICENSE
sudoku_ocr-1.1.3.dist-info/METADATA
sudoku_ocr-1.1.3.dist-info/WHEEL
sudoku_ocr-1.1.3.dist-info/top_level.txt
sudoku_ocr-1.1.3.dist-info/RECORD
